testsheet/__init__.py
testsheet/cli.py
testsheet/test_sheet.py
testsheet-0.3.0.dist-info/LICENSE
testsheet-0.3.0.dist-info/METADATA
testsheet-0.3.0.dist-info/WHEEL
testsheet-0.3.0.dist-info/entry_points.txt
testsheet-0.3.0.dist-info/top_level.txt
testsheet-0.3.0.dist-info/RECORD
