Metadata-Version: 2.2
Name: testsheet
Version: 0.3.0
Summary: A tool to extract test cases from test scripts and export them to Excel.
Author-email: Shivam Kumar Singh <sinhverified@gmail.com>
License: MIT License
Requires-Python: >=3.7
License-File: LICENSE
Requires-Dist: openpyxl>=3.0.0
